colorconfig/__init__.py
colorconfig/colors.py
colorconfig-0.1.0.dist-info/licenses/LICENSE
colorconfig-0.1.0.dist-info/METADATA
colorconfig-0.1.0.dist-info/WHEEL
colorconfig-0.1.0.dist-info/top_level.txt
colorconfig-0.1.0.dist-info/RECORD
