Metadata-Version: 2.4
Name: colorconfig
Version: 0.1.0
Summary: Ein einfaches Farbkonfigurationsmodul für die Konsole
Home-page: https://github.com/jacock123/colorconfig
Author: Otis L. Crossley
Author-email: soon@soon.com
Classifier: Programming Language :: Python :: 3
Classifier: License :: OSI Approved :: MIT License
Classifier: Operating System :: OS Independent
Requires-Python: >=3.6
License-File: LICENSE
Requires-Dist: colorama
Dynamic: author
Dynamic: author-email
Dynamic: classifier
Dynamic: description
Dynamic: description-content-type
Dynamic: home-page
Dynamic: license-file
Dynamic: requires-dist
Dynamic: requires-python
Dynamic: summary
